civil/__init__.py
civil/civil_ai.py
civil/civil_editor.py
civil/civil_lounge.py
civil/civil_server.py
civil/civil_start.py
civil/constants.py
civil/platform.py
civil/properties.py
civil/version.py
civil/data/fonts/Woodtypn.ttf
civil/data/fonts/freesansbold.ttf
civil/data/fonts/lucida.ttf
civil/data/gfx/dialogs/butt-back-moff.png
civil/data/gfx/dialogs/butt-back-mover.png
civil/data/gfx/dialogs/butt-cancel-moff.png
civil/data/gfx/dialogs/butt-cancel-mover.png
civil/data/gfx/dialogs/butt-cancel-small.png
civil/data/gfx/dialogs/butt-credits-moff.png
civil/data/gfx/dialogs/butt-credits-mover.png
civil/data/gfx/dialogs/butt-down-small.png
civil/data/gfx/dialogs/butt-download-moff.png
civil/data/gfx/dialogs/butt-download-mover.png
civil/data/gfx/dialogs/butt-eject-moff.png
civil/data/gfx/dialogs/butt-eject-mover.png
civil/data/gfx/dialogs/butt-fastforward-moff.png
civil/data/gfx/dialogs/butt-fastforward-mover.png
civil/data/gfx/dialogs/butt-forward-moff.png
civil/data/gfx/dialogs/butt-forward-mover.png
civil/data/gfx/dialogs/butt-help-close.png
civil/data/gfx/dialogs/butt-info-moff.png
civil/data/gfx/dialogs/butt-info-mover.png
civil/data/gfx/dialogs/butt-infomenu.png
civil/data/gfx/dialogs/butt-loadgame-moff.png
civil/data/gfx/dialogs/butt-loadgame-mover.png
civil/data/gfx/dialogs/butt-lounge-moff.png
civil/data/gfx/dialogs/butt-lounge-mover.png
civil/data/gfx/dialogs/butt-new-game-moff.png
civil/data/gfx/dialogs/butt-new-game-mover.png
civil/data/gfx/dialogs/butt-ok-moff.png
civil/data/gfx/dialogs/butt-ok-mover.png
civil/data/gfx/dialogs/butt-ok-small.png
civil/data/gfx/dialogs/butt-pause-moff.png
civil/data/gfx/dialogs/butt-pause-mover.png
civil/data/gfx/dialogs/butt-play-moff.png
civil/data/gfx/dialogs/butt-play-mover.png
civil/data/gfx/dialogs/butt-players-moff.png
civil/data/gfx/dialogs/butt-players-mover.png
civil/data/gfx/dialogs/butt-quit-moff.png
civil/data/gfx/dialogs/butt-quit-mover.png
civil-0.84.dist-info/DESCRIPTION.rst
civil-0.84.dist-info/METADATA
civil-0.84.dist-info/RECORD
civil-0.84.dist-info/WHEEL
civil-0.84.dist-info/entry_points.txt
civil-0.84.dist-info/metadata.json
civil-0.84.dist-info/top_level.txt
