Metadata-Version: 2.0
Name: civil
Version: 0.84
Summary: Open source real-time strategy game set during the American Civil war. 
Home-page: UNKNOWN
Author: The Civil Development Team
Author-email: civil@twelvepm.de
License: GPL
Keywords: US Civil war strategy game open source
Platform: UNKNOWN
Classifier: Development Status :: 3 - Alpha
Classifier: Intended Audience :: End Users/Desktop
Classifier: License :: OSI Approved :: GNU General Public License v3 or later (GPLv3+)
Classifier: Operating System :: OS Independent
Classifier: Programming Language :: Python :: 3
Classifier: Topic :: Games/Entertainment :: Real Time Strategy
Requires-Dist: PyGame (>=1.9)
